MACA/__init__.py
MACA_Python-1.0.1.dist-info/LICENSE
MACA_Python-1.0.1.dist-info/METADATA
MACA_Python-1.0.1.dist-info/WHEEL
MACA_Python-1.0.1.dist-info/top_level.txt
MACA_Python-1.0.1.dist-info/RECORD
