Metadata-Version: 2.1
Name: MACA-Python
Version: 1.0.1
Summary: MACA: Marker-based automatic cell-type annotation for single cell expression data
Home-page: https://github.com/ImXman/MACA
Author: Yang Xu
Author-email: yxu71@vols.utk.edu
License: UNKNOWN
Platform: UNKNOWN
Classifier: Programming Language :: Python :: 3.6
Classifier: Programming Language :: Python :: 3.7
Classifier: Programming Language :: Python :: 3.8
Classifier: License :: OSI Approved :: GNU General Public License v3 (GPLv3)
Classifier: Operating System :: OS Independent
Requires-Python: >=3.6
